<?xml version="1.0" encoding="UTF-8"?>
<work-item>
    <field id="author">admin</field>
    <field id="created">2022-11-04 11:28:23.915 +0530</field>
    <field id="description" text-type="text/html">test Jira to polarion</field>
    <field id="hyperlinks">
        <list>
            <struct>
                <item id="role">ref_ext</item>
                <item id="uri">http://localhost:8087/browse/JIRA-19</item>
            </struct>
        </list>
    </field>
    <field id="priority">50.0</field>
    <field id="severity">normal</field>
    <field id="status">To Do</field>
    <field id="title">Shoeb test</field>
    <field id="type">task</field>
</work-item>
