<?xml version="1.0" encoding="UTF-8"?>
<work-item>
    <field id="approvals">
        <list>
            <struct>
                <item id="status">approved</item>
                <item id="user">111</item>
            </struct>
        </list>
    </field>
    <field id="assignee">111</field>
    <field id="author">111</field>
    <field id="created">2022-09-09 12:21:02.221 +0530</field>
    <field id="previousStatus">approved</field>
    <field id="priority">50.0</field>
    <field id="resolution">done</field>
    <field id="resolvedOn">2022-09-14 13:11:55.998 +0530</field>
    <field id="severity">should_have</field>
    <field id="status">draft</field>
    <field id="title">admin: review test</field>
    <field id="type">st</field>
</work-item>
